legwork/R.npy
legwork/__init__.py
legwork/_version.py
legwork/evol.py
legwork/harmonics.npz
legwork/peters_g.npy
legwork/psd.py
legwork/snr.py
legwork/source.py
legwork/strain.py
legwork/utils.py
legwork/verification_binaries.npy
legwork/visualisation.py
legwork/tests/__init__.py
legwork/tests/test_evol.py
legwork/tests/test_psd.py
legwork/tests/test_snrs.py
legwork/tests/test_sources.py
legwork/tests/test_strains.py
legwork/tests/test_utils.py
legwork-0.5.2.dist-info/LICENSE.rst
legwork-0.5.2.dist-info/METADATA
legwork-0.5.2.dist-info/WHEEL
legwork-0.5.2.dist-info/top_level.txt
legwork-0.5.2.dist-info/RECORD
