Metadata-Version: 2.1
Name: legwork
Version: 0.5.2
Summary: A python package to compute gravitational wave evolution and signal to noise ratio calculations for LISA
Home-page: https://github.com/TeamLEGWORK/LEGWORK
Author: Tom Wagg, Katie Breivik
Author-email: tomjwagg@gmail.com
License: MIT
Requires-Python: >=3.11
License-File: LICENSE.rst
Requires-Dist: numba>=0.58
Requires-Dist: numpy>=1.26
Requires-Dist: astropy>=6.1
Requires-Dist: scipy>=1.13
Requires-Dist: matplotlib>=3.8
Requires-Dist: seaborn>=0.13.2
Requires-Dist: schwimmbad>=0.4.2
Provides-Extra: docs
Requires-Dist: sphinx; extra == "docs"
Requires-Dist: matplotlib; extra == "docs"
Provides-Extra: test
Requires-Dist: pytest; extra == "test"
